meshage/__init__.py
meshage/config.py
meshage/messages.py
meshage/parser.py
meshage-0.4.0.dist-info/licenses/LICENSE
meshage-0.4.0.dist-info/WHEEL
meshage-0.4.0.dist-info/METADATA
meshage-0.4.0.dist-info/RECORD
