Metadata-Version: 2.4
Name: meshage
Version: 0.4.0
Summary: Send and receives meshtastic messages via MQTT
Keywords: meshtastic,mqtt
License-Expression: GPL-3.0-only
License-File: LICENSE
Requires-Dist: aiomqtt>=2.4.0
Requires-Dist: cryptography>=45.0.5
Requires-Dist: meshtastic>=2.7.0
Requires-Python: >=3.13
Project-URL: Homepage, https://github.com/andrewbeard/meshage
